Timify/__init__.py
Timify/converter.py
Timify/version.py
Timify-1.0.0.dist-info/METADATA
Timify-1.0.0.dist-info/WHEEL
Timify-1.0.0.dist-info/top_level.txt
Timify-1.0.0.dist-info/RECORD
